twiscrap/__init__.py
twiscrap/items.py
twiscrap/settings.py
twiscrap/spiders/__init__.py
twiscrap/spiders/crawler.py
twiscrap-0.0.1.dist-info/WHEEL
twiscrap-0.0.1.dist-info/METADATA
twiscrap-0.0.1.dist-info/RECORD
